{
  "challengeTracks": {
    "ingredients": { "file": "music/track_exploration.ogg", "volume": -8 },
    "chopping": { "file": "music/track_violence.ogg", "volume": -6 },
    "grinding": { "file": "music/track_violence.ogg", "volume": -6 },
    "stuffing": { "file": "music/track_death_metal.ogg", "volume": -8 },
    "cooking": { "file": "music/track_revenge.ogg", "volume": -8 },
    "blowout": { "file": "music/track_revenge.ogg", "volume": -6 },
    "tasting": { "file": "music/track_dark.ogg", "volume": -10 }
  },
  "victoryTrack": { "file": "music/track_unsettling_victory.ogg", "volume": -8 },
  "enemyTrack": { "file": "music/track_kick_harder.ogg", "volume": -6 },
  "defeatTrack": { "file": "music/track_boss_horror.ogg", "volume": -8 },
  "crossfadeDuration": 2.0,
  "spatialSounds": {
    "fridge_hum": {
      "file": "fridge_hum_loop.ogg",
      "volume": -18,
      "position": [-2.5, 1.0, -2.0],
      "refDistance": 1.0,
      "maxDistance": 8.0,
      "rolloffFactor": 1.5,
      "loop": true
    },
    "grinder_idle": {
      "file": "grinder_idle_loop.ogg",
      "volume": -20,
      "position": [1.5, 0.9, -1.5],
      "refDistance": 0.8,
      "maxDistance": 6.0,
      "rolloffFactor": 2.0,
      "loop": true
    },
    "stove_sizzle": {
      "file": "sizzle_loop_1.ogg",
      "volume": -16,
      "position": [2.0, 0.9, 1.5],
      "refDistance": 1.0,
      "maxDistance": 7.0,
      "rolloffFactor": 1.5,
      "loop": true
    },
    "drain_drip": {
      "file": "drain_drip_loop.ogg",
      "volume": -22,
      "position": [0.0, 0.0, 0.0],
      "refDistance": 0.5,
      "maxDistance": 5.0,
      "rolloffFactor": 2.5,
      "loop": true
    }
  }
}
